{"id":"fh_1611813734553","created_at":1611813734553,"updated_at":1611834305974,"title":"构建属于自己的vue-npm组件库","data":{"root":{"data":{"id":"c8ujyoqzl0w0","created":1611812831672,"text":"构建属于自己的vue-npm组件库","expandState":"expand"},"children":[{"data":{"id":"c8ujz9f4vco0","created":1611812876667,"text":"事前准备条件","layout":null,"expandState":"expand"},"children":[{"data":{"id":"c8ujzwhgie80","created":1611812926874,"text":"编辑器自选（推荐VsCode）","layout":null,"expandState":"expand"},"children":[{"data":{"id":"c8uk6gufq5c0","created":1611813441379,"text":"VsCode下载地址：https://code.visualstudio.com/download","layout":null,"expandState":"expand","hyperlink":"https://code.visualstudio.com/download","hyperlinkTitle":"下载地址"},"children":[]},{"data":{"id":"c8uk66x20eg0","created":1611813419770,"text":"VsCode安装指导：https://www.cnblogs.com/csji/p/13558221.html","layout":null,"expandState":"expand","hyperlink":"https://www.cnblogs.com/csji/p/13558221.html","hyperlinkTitle":"安装指导"},"children":[]}]},{"data":{"id":"c8ukdpadg880","created":1611814008306,"text":"安装git","layout":null,"expandState":"expand"},"children":[{"data":{"id":"c8ukf9yw58o0","created":1611814131689,"text":"代码保存仓库：https://github.com/","hyperlink":"https://github.com/","hyperlinkTitle":"github","layout":null,"expandState":"expand"},"children":[]}]},{"data":{"id":"c8ujzged2bc0","created":1611812891858,"text":"Node.js","layout":null,"expandState":"expand"},"children":[{"data":{"id":"c8uk0t3xkmo0","created":1611812997890,"text":"下载地址：http://nodejs.cn/download/ ","layout_right_offset":{"x":3,"y":1},"layout":null,"expandState":"expand","hyperlink":"http://nodejs.cn/download/","hyperlinkTitle":"Node.js"},"children":[]},{"data":{"id":"c8uk8dlgrm80","created":1611813591035,"text":"相关博文：https://www.cnblogs.com/lgx5/p/10732016.html","layout_right_offset":{"x":1,"y":-5},"layout":null,"expandState":"expand","hyperlink":"https://www.cnblogs.com/lgx5/p/10732016.html","hyperlinkTitle":"安装指导"},"children":[]},{"data":{"id":"c8uk8pgxf2g0","created":1611813616882,"text":"可选扩展：nrm","layout":null,"expandState":"expand"},"children":[{"data":{"id":"c8uk8tss7uo0","created":1611813626306,"text":"博客链接：https://juejin.cn/post/6922024602453426190 ","layout":null,"expandState":"expand","hyperlink":"https://juejin.cn/post/6922024602453426190","hyperlinkTitle":"夹杂私货，应该没人发现吧٩(๑>◡<๑)۶"},"children":[]}]}]},{"data":{"id":"c8ujzj88f8g0","created":1611812898018,"text":"vue&vue-cli","layout":null,"expandState":"expand"},"children":[{"data":{"id":"c8uk4dah4dc0","created":1611813276914,"text":"参考链接：https://cli.vuejs.org/zh/guide/installation.html","layout":null,"expandState":"expand","hyperlink":"https://cli.vuejs.org/zh/guide/installation.html","hyperlinkTitle":"超官方链接"},"children":[]},{"data":{"id":"c8uk49hoddk0","created":1611813268642,"text":"全局安装vue-cli：npm install -g @vue/cli","layout":null,"expandState":"expand"},"children":[]}]},{"data":{"id":"c8uke3vd0ww0","created":1611814040050,"text":"注册npm账号","layout":null,"expandState":"expand"},"children":[{"data":{"id":"c8ukf12g2d40","created":1611814112313,"text":"官网链接：https://www.npmjs.com/","layout":null,"expandState":"expand","hyperlink":"https://www.npmjs.com/","hyperlinkTitle":"npm官网有点慢可能"},"children":[]}]},{"data":{"id":"c8ukah6b9pc0","created":1611813755554,"text":"可选扩展","layout":null,"expandState":"expand"},"children":[{"data":{"id":"c8ukh1x51ag0","created":1611814270897,"text":"一点点webpack的知识，其实不会也ok","layout":null,"expandState":"expand"},"children":[]},{"data":{"id":"c8ukakppng00","created":1611813763257,"text":"element源码参考","layout":null,"expandState":"expand"},"children":[{"data":{"id":"c8ukau64eag0","created":1611813783841,"text":"https://github.com/ElemeFE/element","layout":null,"expandState":"expand","hyperlink":"https://github.com/ElemeFE/element","hyperlinkTitle":"Element源码"},"children":[]}]}]}]},{"data":{"id":"c8ujzdbrx680","created":1611812885171,"text":"构建&使用","layout":null,"expandState":"expand"},"children":[{"data":{"id":"c8uki458tn40","created":1611814354105,"text":"创建组件库项目","layout":null,"expandState":"expand"},"children":[{"data":{"id":"c8uki8m9pcg0","created":1611814363841,"text":"vue create xd-test-ui","layout":null,"expandState":"expand"},"children":[]},{"data":{"id":"c8ukiv6cle80","created":1611814412945,"text":"调整目录结构","layout":null,"expandState":"expand"},"children":[{"data":{"id":"c8ukjfdnagw0","created":1611814456921,"text":"...\n|-- examples      // 原 src 目录，改成 examples 用作示例展示\n|-- packages      // 新增 packages 用于编写存放组件\n...","layout":null,"expandState":"expand"},"children":[]}]}]},{"data":{"id":"c8ukl7pn0rk0","created":1611814596961,"text":"项目配置调整","layout":null,"expandState":"expand"},"children":[{"data":{"id":"c8ukmglmxr40","created":1611814694674,"text":"根目录新增 vue.config.js 配置文件","resource":[],"progress":null,"layout":null,"expandState":"expand"},"children":[]}]},{"data":{"id":"c8ukokt3nc80","created":1611814860561,"text":"编写组件","layout":null,"expandState":"expand"},"children":[{"data":{"id":"c8ukpi9hm5s0","created":1611814933385,"text":"在packages下新建组件文件夹button 同级新建 文件index.js","layout":null,"expandState":"expand"},"children":[]},{"data":{"id":"c8uku61mhjc0","created":1611815298609,"text":"在button文件夹下新建src/button.vue和index.js","layout":null,"expandState":"expand"},"children":[]},{"data":{"id":"c8ukvzyd6uo0","created":1611815442080,"text":"最终的结构：\n|——\n|——packages\n|   |——index.js\n|   |——button\n|      |——index.js\n|      |——src\n|         |——button.vue\n|——","layout":null,"expandState":"expand"},"children":[]},{"data":{"id":"c8ukxze56aw0","created":1611815597585,"text":"着手编写相应的组件代码","layout":null},"children":[]}]},{"data":{"id":"c8ul37d08800","created":1611816006752,"text":"组件打包&发布","layout":null},"children":[{"data":{"id":"c8ul3slg5ts0","created":1611816052975,"text":"package.json文件配置","layout":null},"children":[{"data":{"id":"c8ul40rh0ns0","created":1611816070753,"text":"\"description\": \"基于Vue搭建的一个基础组件库。\",\n  \"main\": \"lib/xd-ui.umd.min.js\",\n  \"private\": false,\n  \"license\": \"MIT\",\n  \"scripts\": {\n\t\"serve\": \"vue-cli-service serve\",\n\t\"build\": \"vue-cli-service build\",\n\t\"lint\": \"vue-cli-service lint\",\n\t\"lib\": \"vue-cli-service build --target lib --name xd-test-ui --dest lib packages/index.js\"\n  },","layout":null},"children":[]}]},{"data":{"id":"c8ul6kqsep40","created":1611816270976,"text":"执行打包编译命令","layout":null},"children":[{"data":{"id":"c8ul6yidztk0","created":1611816300943,"text":"npm run lib","layout":null},"children":[]},{"data":{"id":"c8ul7dlmz400","created":1611816333791,"text":"编译完成后会出现lib文件（需要发布的目标文件）","layout":null},"children":[]}]},{"data":{"id":"c8ul7or25n40","created":1611816358063,"text":"发布npm组件库","layout":null},"children":[{"data":{"id":"c8ul8lba2v40","created":1611816428943,"text":"切换npm源","layout":null},"children":[{"data":{"id":"c8ul85j0qzs0","created":1611816394583,"text":"有些同学可能是taobao的源首先换回npm源：npm config set registry http://registry.npmjs.org ","layout":null},"children":[]},{"data":{"id":"c8ul8wzveso0","created":1611816454375,"text":"或者使用之前说的 nrm 使用nrm use taobao 换源","layout":null},"children":[]}]},{"data":{"id":"c8ul96tjacw0","created":1611816475759,"text":"登录到npm","layout":null},"children":[{"data":{"id":"c8ula3krp9c0","created":1611816547063,"text":"首先去官网注册个账号，上面有官网地址","layout":null},"children":[]},{"data":{"id":"c8ulabhh0cw0","created":1611816564279,"text":"使用命令：npm login 然后输入账号、密码、邮箱","layout":null},"children":[]}]},{"data":{"id":"c8ulav4000g0","created":1611816606999,"text":"发布到npm","layout":null},"children":[{"data":{"id":"c8ulaxvi2mo0","created":1611816613016,"text":"npm punlish","layout":null},"children":[]}]}]}]},{"data":{"id":"c8ulbmfyx9c0","created":1611816666496,"text":"引入自己构建好的npm","layout":null},"children":[{"data":{"id":"c8ulddaqxyo0","created":1611816803318,"text":"在组件库内测试","layout":null},"children":[{"data":{"id":"c8uldwpqd8g0","created":1611816845582,"text":"引入组件内容即可","layout":null},"children":[]}]},{"data":{"id":"c8uldp7z45c0","created":1611816829271,"text":"下载npm包测试","layout":null},"children":[{"data":{"id":"c8uledzl6og0","created":1611816883184,"text":"创建vue-cli项目","layout":null},"children":[]},{"data":{"id":"c8ule2nj8wg0","created":1611816858510,"text":"npm install xd-test-ui","layout":null},"children":[]},{"data":{"id":"c8ule95zbts0","created":1611816872686,"text":"main.js中配置引入","layout":null},"children":[]},{"data":{"id":"c8ulelszco80","created":1611816900198,"text":"运行测试","layout":null},"children":[]}]}]}]}]},"template":"right","theme":"fresh-blue","version":"1.4.43"}}